odoo9_addon_connector_prestashop_manufacturer-9.0.1.0.0.99.dev12-nspkg.pth
odoo_addons/connector_prestashop_manufacturer/README.rst
odoo_addons/connector_prestashop_manufacturer/__init__.py
odoo_addons/connector_prestashop_manufacturer/__openerp__.py
odoo_addons/connector_prestashop_manufacturer/consumer.py
odoo_addons/connector_prestashop_manufacturer/data/connector_prestashop_manufacturer_data.xml
odoo_addons/connector_prestashop_manufacturer/data/cron.xml
odoo_addons/connector_prestashop_manufacturer/models/__init__.py
odoo_addons/connector_prestashop_manufacturer/models/prestashop_backend/__init__.py
odoo_addons/connector_prestashop_manufacturer/models/prestashop_backend/common.py
odoo_addons/connector_prestashop_manufacturer/models/product_template/__init__.py
odoo_addons/connector_prestashop_manufacturer/models/product_template/exporter.py
odoo_addons/connector_prestashop_manufacturer/models/product_template/importer.py
odoo_addons/connector_prestashop_manufacturer/models/res_partner/__init__.py
odoo_addons/connector_prestashop_manufacturer/models/res_partner/common.py
odoo_addons/connector_prestashop_manufacturer/models/res_partner/exporter.py
odoo_addons/connector_prestashop_manufacturer/models/res_partner/importer.py
odoo_addons/connector_prestashop_manufacturer/security/ir.model.access.csv
odoo_addons/connector_prestashop_manufacturer/static/description/icon.png
odoo_addons/connector_prestashop_manufacturer/static/description/icon.svg
odoo_addons/connector_prestashop_manufacturer/tests/__init__.py
odoo_addons/connector_prestashop_manufacturer/tests/test_import_manufacturer.py
odoo_addons/connector_prestashop_manufacturer/unit/__init__.py
odoo_addons/connector_prestashop_manufacturer/unit/binder.py
odoo_addons/connector_prestashop_manufacturer/views/connector_prestashop_menu.xml
odoo_addons/connector_prestashop_manufacturer/views/partner_view.xml
odoo_addons/connector_prestashop_manufacturer/views/prestashop_model_view.xml
odoo9_addon_connector_prestashop_manufacturer-9.0.1.0.0.99.dev12.dist-info/METADATA
odoo9_addon_connector_prestashop_manufacturer-9.0.1.0.0.99.dev12.dist-info/WHEEL
odoo9_addon_connector_prestashop_manufacturer-9.0.1.0.0.99.dev12.dist-info/namespace_packages.txt
odoo9_addon_connector_prestashop_manufacturer-9.0.1.0.0.99.dev12.dist-info/top_level.txt
odoo9_addon_connector_prestashop_manufacturer-9.0.1.0.0.99.dev12.dist-info/RECORD
