Metadata-Version: 2.1
Name: odoo9-addon-connector-prestashop-manufacturer
Version: 9.0.1.0.0.99.dev12
Summary: Import manufacturers from PrestaShop
Home-page: https://odoo-community.org/
Author: Tecnativa, Camptocamp SA Odoo Community Association (OCA)
Author-email: support@odoo-community.org
License: AGPL-3
Platform: UNKNOWN
Classifier: Programming Language :: Python
Classifier: Framework :: Odoo
Classifier: License :: OSI Approved :: GNU Affero General Public License v3
Requires-Python: ~=2.7
Requires-Dist: odoo9-addon-connector-prestashop
Requires-Dist: odoo9-addon-connector-prestashop-catalog-manager
Requires-Dist: odoo9-addon-product-manufacturer
Requires-Dist: odoo (<9.1a,>=9.0a)
